{
    "columns": [
        {
            "name": "_Id",
            "type": "int"
        },
        {
            "name": "_CategoryIndex",
            "type": "int"
        },
        {
            "name": "_DefaultPage",
            "type": "int"
        }
    ],
    "datas": [
        {
            "_Id": 1,
            "_CategoryIndex": 1,
            "_DefaultPage": 1
        },
        {
            "_Id": 2,
            "_CategoryIndex": 2,
            "_DefaultPage": 10
        },
        {
            "_Id": 3,
            "_CategoryIndex": 3,
            "_DefaultPage": 12
        },
        {
            "_Id": 4,
            "_CategoryIndex": 4,
            "_DefaultPage": 14
        },
        {
            "_Id": 5,
            "_CategoryIndex": 5,
            "_DefaultPage": 17
        },
        {
            "_Id": 6,
            "_CategoryIndex": 9,
            "_DefaultPage": 29
        },
        {
            "_Id": 7,
            "_CategoryIndex": 10,
            "_DefaultPage": 36
        },
        {
            "_Id": 8,
            "_CategoryIndex": 11,
            "_DefaultPage": 38
        }
    ]
}