{
    "columns": [
        {
            "name": "_Id",
            "type": "int"
        },
        {
            "name": "_Rank",
            "type": "int"
        },
        {
            "name": "_ItemID",
            "type": "int"
        },
        {
            "name": "_ItemRare",
            "type": "int"
        },
        {
            "name": "_ItemCount",
            "type": "int"
        },
        {
            "name": "_Ely",
            "type": "int"
        },
        {
            "name": "_Description",
            "type": "string"
        },
        {
            "name": "_IconFile",
            "type": "int"
        },
        {
            "name": "_IconIndex",
            "type": "int"
        },
        {
            "name": "_Use",
            "type": "bool"
        },
        {
            "name": "_Fx1",
            "type": "int"
        },
        {
            "name": "_Fx2",
            "type": "int"
        },
        {
            "name": "_Message",
            "type": "string"
        },
        {
            "name": "_Red",
            "type": "int"
        },
        {
            "name": "_Green",
            "type": "int"
        },
        {
            "name": "_Blue",
            "type": "int"
        },
        {
            "name": "_SoundEffect",
            "type": "int"
        },
        {
            "name": "_Name",
            "type": "string"
        }
    ],
    "datas": [
        {
            "_Id": 1,
            "_Rank": 1,
            "_ItemID": 164402658,
            "_ItemRare": 5,
            "_ItemCount": 1,
            "_Ely": 0,
            "_Description": "",
            "_IconFile": 10001112,
            "_IconIndex": 90,
            "_Use": true,
            "_Fx1": 22457,
            "_Fx2": 22467,
            "_Message": "☆☆☆☆☆ 1등 당첨 ☆☆☆☆☆",
            "_Red": 255,
            "_Green": 214,
            "_Blue": 71,
            "_SoundEffect": 8106,
            "_Name": ""
        },
        {
            "_Id": 2,
            "_Rank": 1,
            "_ItemID": 170130224,
            "_ItemRare": 1,
            "_ItemCount": 1,
            "_Ely": 0,
            "_Description": "",
            "_IconFile": 10001323,
            "_IconIndex": 133,
            "_Use": true,
            "_Fx1": 22457,
            "_Fx2": 22467,
            "_Message": "☆☆☆☆☆ 1등 당첨 ☆☆☆☆☆",
            "_Red": 255,
            "_Green": 214,
            "_Blue": 71,
            "_SoundEffect": 8106,
            "_Name": ""
        },
        {
            "_Id": 3,
            "_Rank": 1,
            "_ItemID": 190147780,
            "_ItemRare": 1,
            "_ItemCount": 1,
            "_Ely": 0,
            "_Description": "",
            "_IconFile": 10001208,
            "_IconIndex": 164,
            "_Use": true,
            "_Fx1": 22457,
            "_Fx2": 22467,
            "_Message": "☆☆☆☆☆ 1등 당첨 ☆☆☆☆☆",
            "_Red": 255,
            "_Green": 214,
            "_Blue": 71,
            "_SoundEffect": 8106,
            "_Name": ""
        },
        {
            "_Id": 4,
            "_Rank": 1,
            "_ItemID": 190148026,
            "_ItemRare": 1,
            "_ItemCount": 1,
            "_Ely": 0,
            "_Description": "",
            "_IconFile": 10001207,
            "_IconIndex": 249,
            "_Use": true,
            "_Fx1": 22457,
            "_Fx2": 22467,
            "_Message": "☆☆☆☆☆ 1등 당첨 ☆☆☆☆☆",
            "_Red": 255,
            "_Green": 214,
            "_Blue": 71,
            "_SoundEffect": 8106,
            "_Name": ""
        },
        {
            "_Id": 5,
            "_Rank": 1,
            "_ItemID": 190147013,
            "_ItemRare": 1,
            "_ItemCount": 150,
            "_Ely": 0,
            "_Description": "",
            "_IconFile": 10001326,
            "_IconIndex": 122,
            "_Use": true,
            "_Fx1": 22457,
            "_Fx2": 22467,
            "_Message": "☆☆☆☆☆ 1등 당첨 ☆☆☆☆☆",
            "_Red": 255,
            "_Green": 214,
            "_Blue": 71,
            "_SoundEffect": 8106,
            "_Name": ""
        },
        {
            "_Id": 6,
            "_Rank": 1,
            "_ItemID": 190147204,
            "_ItemRare": 1,
            "_ItemCount": 5,
            "_Ely": 0,
            "_Description": "",
            "_IconFile": 10001306,
            "_IconIndex": 138,
            "_Use": true,
            "_Fx1": 22457,
            "_Fx2": 22467,
            "_Message": "☆☆☆☆☆ 1등 당첨 ☆☆☆☆☆",
            "_Red": 255,
            "_Green": 214,
            "_Blue": 71,
            "_SoundEffect": 8106,
            "_Name": ""
        },
        {
            "_Id": 7,
            "_Rank": 2,
            "_ItemID": 170130225,
            "_ItemRare": 1,
            "_ItemCount": 1,
            "_Ely": 0,
            "_Description": "",
            "_IconFile": 10001323,
            "_IconIndex": 133,
            "_Use": true,
            "_Fx1": 22458,
            "_Fx2": 22468,
            "_Message": "★★★2등 당첨★★★",
            "_Red": 255,
            "_Green": 255,
            "_Blue": 255,
            "_SoundEffect": 8107,
            "_Name": ""
        },
        {
            "_Id": 8,
            "_Rank": 2,
            "_ItemID": 190147988,
            "_ItemRare": 1,
            "_ItemCount": 1,
            "_Ely": 0,
            "_Description": "",
            "_IconFile": 10001325,
            "_IconIndex": 69,
            "_Use": true,
            "_Fx1": 22458,
            "_Fx2": 22468,
            "_Message": "★★★2등 당첨★★★",
            "_Red": 255,
            "_Green": 255,
            "_Blue": 255,
            "_SoundEffect": 8107,
            "_Name": ""
        },
        {
            "_Id": 9,
            "_Rank": 2,
            "_ItemID": 170171241,
            "_ItemRare": 1,
            "_ItemCount": 300,
            "_Ely": 0,
            "_Description": "",
            "_IconFile": 10001314,
            "_IconIndex": 87,
            "_Use": true,
            "_Fx1": 22458,
            "_Fx2": 22468,
            "_Message": "★★★2등 당첨★★★",
            "_Red": 255,
            "_Green": 255,
            "_Blue": 255,
            "_SoundEffect": 8107,
            "_Name": ""
        },
        {
            "_Id": 10,
            "_Rank": 2,
            "_ItemID": 180202202,
            "_ItemRare": 1,
            "_ItemCount": 1,
            "_Ely": 0,
            "_Description": "",
            "_IconFile": 10001326,
            "_IconIndex": 64,
            "_Use": true,
            "_Fx1": 22458,
            "_Fx2": 22468,
            "_Message": "★★★2등 당첨★★★",
            "_Red": 255,
            "_Green": 255,
            "_Blue": 255,
            "_SoundEffect": 8107,
            "_Name": ""
        },
        {
            "_Id": 11,
            "_Rank": 2,
            "_ItemID": 170196077,
            "_ItemRare": 1,
            "_ItemCount": 1,
            "_Ely": 0,
            "_Description": "",
            "_IconFile": 10001304,
            "_IconIndex": 247,
            "_Use": true,
            "_Fx1": 22458,
            "_Fx2": 22468,
            "_Message": "★★★2등 당첨★★★",
            "_Red": 255,
            "_Green": 255,
            "_Blue": 255,
            "_SoundEffect": 8107,
            "_Name": ""
        },
        {
            "_Id": 12,
            "_Rank": 3,
            "_ItemID": 170130226,
            "_ItemRare": 1,
            "_ItemCount": 1,
            "_Ely": 0,
            "_Description": "",
            "_IconFile": 10001323,
            "_IconIndex": 133,
            "_Use": true,
            "_Fx1": 22459,
            "_Fx2": 22469,
            "_Message": "☆3등 당첨☆",
            "_Red": 198,
            "_Green": 156,
            "_Blue": 109,
            "_SoundEffect": 8107,
            "_Name": ""
        },
        {
            "_Id": 13,
            "_Rank": 3,
            "_ItemID": 190148182,
            "_ItemRare": 1,
            "_ItemCount": 10,
            "_Ely": 0,
            "_Description": "",
            "_IconFile": 10001300,
            "_IconIndex": 93,
            "_Use": true,
            "_Fx1": 22459,
            "_Fx2": 22469,
            "_Message": "☆3등 당첨☆",
            "_Red": 198,
            "_Green": 156,
            "_Blue": 109,
            "_SoundEffect": 8107,
            "_Name": ""
        },
        {
            "_Id": 14,
            "_Rank": 3,
            "_ItemID": 190144674,
            "_ItemRare": 1,
            "_ItemCount": 300,
            "_Ely": 0,
            "_Description": "",
            "_IconFile": 10001309,
            "_IconIndex": 7,
            "_Use": true,
            "_Fx1": 22459,
            "_Fx2": 22469,
            "_Message": "☆3등 당첨☆",
            "_Red": 198,
            "_Green": 156,
            "_Blue": 109,
            "_SoundEffect": 8107,
            "_Name": ""
        },
        {
            "_Id": 15,
            "_Rank": 3,
            "_ItemID": 190146652,
            "_ItemRare": 1,
            "_ItemCount": 2,
            "_Ely": 0,
            "_Description": "",
            "_IconFile": 10001312,
            "_IconIndex": 236,
            "_Use": true,
            "_Fx1": 22459,
            "_Fx2": 22469,
            "_Message": "☆3등 당첨☆",
            "_Red": 198,
            "_Green": 156,
            "_Blue": 109,
            "_SoundEffect": 8107,
            "_Name": ""
        },
        {
            "_Id": 16,
            "_Rank": 3,
            "_ItemID": 170195951,
            "_ItemRare": 1,
            "_ItemCount": 1,
            "_Ely": 0,
            "_Description": "",
            "_IconFile": 10001304,
            "_IconIndex": 247,
            "_Use": true,
            "_Fx1": 22459,
            "_Fx2": 22469,
            "_Message": "☆3등 당첨☆",
            "_Red": 198,
            "_Green": 156,
            "_Blue": 109,
            "_SoundEffect": 8107,
            "_Name": ""
        },
        {
            "_Id": 17,
            "_Rank": 4,
            "_ItemID": 190146494,
            "_ItemRare": 1,
            "_ItemCount": 4,
            "_Ely": 0,
            "_Description": "",
            "_IconFile": 10001313,
            "_IconIndex": 138,
            "_Use": true,
            "_Fx1": 22460,
            "_Fx2": 22470,
            "_Message": "4등이다",
            "_Red": 255,
            "_Green": 143,
            "_Blue": 147,
            "_SoundEffect": 8108,
            "_Name": ""
        },
        {
            "_Id": 18,
            "_Rank": 4,
            "_ItemID": 190195489,
            "_ItemRare": 1,
            "_ItemCount": 100,
            "_Ely": 0,
            "_Description": "",
            "_IconFile": 10001303,
            "_IconIndex": 139,
            "_Use": true,
            "_Fx1": 22460,
            "_Fx2": 22470,
            "_Message": "4등이다",
            "_Red": 255,
            "_Green": 143,
            "_Blue": 147,
            "_SoundEffect": 8108,
            "_Name": ""
        },
        {
            "_Id": 19,
            "_Rank": 4,
            "_ItemID": 190148475,
            "_ItemRare": 1,
            "_ItemCount": 50,
            "_Ely": 0,
            "_Description": "",
            "_IconFile": 10001320,
            "_IconIndex": 234,
            "_Use": true,
            "_Fx1": 22460,
            "_Fx2": 22470,
            "_Message": "4등이다",
            "_Red": 255,
            "_Green": 143,
            "_Blue": 147,
            "_SoundEffect": 8108,
            "_Name": ""
        },
        {
            "_Id": 20,
            "_Rank": 4,
            "_ItemID": 190146650,
            "_ItemRare": 1,
            "_ItemCount": 3,
            "_Ely": 0,
            "_Description": "",
            "_IconFile": 10001304,
            "_IconIndex": 11,
            "_Use": true,
            "_Fx1": 22460,
            "_Fx2": 22470,
            "_Message": "4등이다",
            "_Red": 255,
            "_Green": 143,
            "_Blue": 147,
            "_SoundEffect": 8108,
            "_Name": ""
        },
        {
            "_Id": 21,
            "_Rank": 4,
            "_ItemID": 190192111,
            "_ItemRare": 1,
            "_ItemCount": 10,
            "_Ely": 0,
            "_Description": "",
            "_IconFile": 10001304,
            "_IconIndex": 254,
            "_Use": true,
            "_Fx1": 22460,
            "_Fx2": 22470,
            "_Message": "4등이다",
            "_Red": 255,
            "_Green": 143,
            "_Blue": 147,
            "_SoundEffect": 8108,
            "_Name": ""
        },
        {
            "_Id": 22,
            "_Rank": 5,
            "_ItemID": 170171340,
            "_ItemRare": 1,
            "_ItemCount": 30,
            "_Ely": 0,
            "_Description": "",
            "_IconFile": 10001300,
            "_IconIndex": 45,
            "_Use": true,
            "_Fx1": 22461,
            "_Fx2": 22471,
            "_Message": "5등이다",
            "_Red": 255,
            "_Green": 143,
            "_Blue": 147,
            "_SoundEffect": 8108,
            "_Name": ""
        },
        {
            "_Id": 23,
            "_Rank": 5,
            "_ItemID": 170194888,
            "_ItemRare": 1,
            "_ItemCount": 1,
            "_Ely": 0,
            "_Description": "",
            "_IconFile": 10001314,
            "_IconIndex": 24,
            "_Use": true,
            "_Fx1": 22461,
            "_Fx2": 22471,
            "_Message": "5등이다",
            "_Red": 255,
            "_Green": 143,
            "_Blue": 147,
            "_SoundEffect": 8108,
            "_Name": ""
        },
        {
            "_Id": 24,
            "_Rank": 5,
            "_ItemID": 170193811,
            "_ItemRare": 1,
            "_ItemCount": 1,
            "_Ely": 0,
            "_Description": "",
            "_IconFile": 10001323,
            "_IconIndex": 125,
            "_Use": true,
            "_Fx1": 22461,
            "_Fx2": 22471,
            "_Message": "5등이다",
            "_Red": 255,
            "_Green": 143,
            "_Blue": 147,
            "_SoundEffect": 8108,
            "_Name": ""
        },
        {
            "_Id": 25,
            "_Rank": 5,
            "_ItemID": 190146091,
            "_ItemRare": 1,
            "_ItemCount": 1,
            "_Ely": 0,
            "_Description": "",
            "_IconFile": 10001321,
            "_IconIndex": 21,
            "_Use": true,
            "_Fx1": 22461,
            "_Fx2": 22471,
            "_Message": "5등이다",
            "_Red": 255,
            "_Green": 143,
            "_Blue": 147,
            "_SoundEffect": 8108,
            "_Name": ""
        },
        {
            "_Id": 26,
            "_Rank": 6,
            "_ItemID": 300199016,
            "_ItemRare": 1,
            "_ItemCount": 2,
            "_Ely": 0,
            "_Description": "",
            "_IconFile": 10001319,
            "_IconIndex": 195,
            "_Use": true,
            "_Fx1": 22462,
            "_Fx2": 22472,
            "_Message": "6등이다",
            "_Red": 255,
            "_Green": 143,
            "_Blue": 147,
            "_SoundEffect": 8108,
            "_Name": ""
        },
        {
            "_Id": 27,
            "_Rank": 6,
            "_ItemID": 190147983,
            "_ItemRare": 1,
            "_ItemCount": 20,
            "_Ely": 0,
            "_Description": "",
            "_IconFile": 10001325,
            "_IconIndex": 70,
            "_Use": true,
            "_Fx1": 22462,
            "_Fx2": 22472,
            "_Message": "6등이다",
            "_Red": 255,
            "_Green": 143,
            "_Blue": 147,
            "_SoundEffect": 8108,
            "_Name": ""
        },
        {
            "_Id": 28,
            "_Rank": 6,
            "_ItemID": 170196080,
            "_ItemRare": 1,
            "_ItemCount": 50,
            "_Ely": 0,
            "_Description": "",
            "_IconFile": 10001304,
            "_IconIndex": 247,
            "_Use": true,
            "_Fx1": 22462,
            "_Fx2": 22472,
            "_Message": "6등이다",
            "_Red": 255,
            "_Green": 143,
            "_Blue": 147,
            "_SoundEffect": 8108,
            "_Name": ""
        },
        {
            "_Id": 29,
            "_Rank": 6,
            "_ItemID": 170196081,
            "_ItemRare": 1,
            "_ItemCount": 50,
            "_Ely": 0,
            "_Description": "",
            "_IconFile": 10001304,
            "_IconIndex": 247,
            "_Use": true,
            "_Fx1": 22462,
            "_Fx2": 22472,
            "_Message": "6등이다",
            "_Red": 255,
            "_Green": 143,
            "_Blue": 147,
            "_SoundEffect": 8108,
            "_Name": ""
        },
        {
            "_Id": 30,
            "_Rank": 6,
            "_ItemID": 170196082,
            "_ItemRare": 1,
            "_ItemCount": 50,
            "_Ely": 0,
            "_Description": "",
            "_IconFile": 10001304,
            "_IconIndex": 247,
            "_Use": true,
            "_Fx1": 22462,
            "_Fx2": 22472,
            "_Message": "6등이다",
            "_Red": 255,
            "_Green": 143,
            "_Blue": 147,
            "_SoundEffect": 8108,
            "_Name": ""
        },
        {
            "_Id": 31,
            "_Rank": 6,
            "_ItemID": 170196083,
            "_ItemRare": 1,
            "_ItemCount": 50,
            "_Ely": 0,
            "_Description": "",
            "_IconFile": 10001304,
            "_IconIndex": 247,
            "_Use": true,
            "_Fx1": 22462,
            "_Fx2": 22472,
            "_Message": "6등이다",
            "_Red": 255,
            "_Green": 143,
            "_Blue": 147,
            "_SoundEffect": 8108,
            "_Name": ""
        },
        {
            "_Id": 32,
            "_Rank": 7,
            "_ItemID": 300199711,
            "_ItemRare": 1,
            "_ItemCount": 1,
            "_Ely": 0,
            "_Description": "",
            "_IconFile": 10001311,
            "_IconIndex": 65,
            "_Use": true,
            "_Fx1": 22463,
            "_Fx2": 22473,
            "_Message": "7등이다",
            "_Red": 255,
            "_Green": 143,
            "_Blue": 147,
            "_SoundEffect": 8108,
            "_Name": ""
        },
        {
            "_Id": 33,
            "_Rank": 7,
            "_ItemID": 170130174,
            "_ItemRare": 1,
            "_ItemCount": 1,
            "_Ely": 0,
            "_Description": "",
            "_IconFile": 10001323,
            "_IconIndex": 134,
            "_Use": true,
            "_Fx1": 22463,
            "_Fx2": 22473,
            "_Message": "7등이다",
            "_Red": 255,
            "_Green": 143,
            "_Blue": 147,
            "_SoundEffect": 8108,
            "_Name": ""
        },
        {
            "_Id": 34,
            "_Rank": 7,
            "_ItemID": 170171280,
            "_ItemRare": 1,
            "_ItemCount": 1,
            "_Ely": 0,
            "_Description": "",
            "_IconFile": 10001306,
            "_IconIndex": 105,
            "_Use": true,
            "_Fx1": 22463,
            "_Fx2": 22473,
            "_Message": "7등이다",
            "_Red": 255,
            "_Green": 143,
            "_Blue": 147,
            "_SoundEffect": 8108,
            "_Name": ""
        },
        {
            "_Id": 35,
            "_Rank": 7,
            "_ItemID": 170195950,
            "_ItemRare": 1,
            "_ItemCount": 50,
            "_Ely": 0,
            "_Description": "",
            "_IconFile": 10001313,
            "_IconIndex": 210,
            "_Use": true,
            "_Fx1": 22463,
            "_Fx2": 22473,
            "_Message": "7등이다",
            "_Red": 255,
            "_Green": 143,
            "_Blue": 147,
            "_SoundEffect": 8108,
            "_Name": ""
        },
        {
            "_Id": 36,
            "_Rank": 7,
            "_ItemID": 170195949,
            "_ItemRare": 1,
            "_ItemCount": 50,
            "_Ely": 0,
            "_Description": "",
            "_IconFile": 10001313,
            "_IconIndex": 210,
            "_Use": true,
            "_Fx1": 22463,
            "_Fx2": 22473,
            "_Message": "7등이다",
            "_Red": 255,
            "_Green": 143,
            "_Blue": 147,
            "_SoundEffect": 8108,
            "_Name": ""
        },
        {
            "_Id": 37,
            "_Rank": 7,
            "_ItemID": 170196544,
            "_ItemRare": 1,
            "_ItemCount": 1,
            "_Ely": 0,
            "_Description": "",
            "_IconFile": 10001323,
            "_IconIndex": 134,
            "_Use": true,
            "_Fx1": 22463,
            "_Fx2": 22473,
            "_Message": "7등이다",
            "_Red": 255,
            "_Green": 143,
            "_Blue": 147,
            "_SoundEffect": 8108,
            "_Name": ""
        },
        {
            "_Id": 38,
            "_Rank": 8,
            "_ItemID": 170171254,
            "_ItemRare": 1,
            "_ItemCount": 1,
            "_Ely": 0,
            "_Description": "",
            "_IconFile": 10001306,
            "_IconIndex": 106,
            "_Use": true,
            "_Fx1": 22464,
            "_Fx2": 22474,
            "_Message": "8등이다",
            "_Red": 179,
            "_Green": 163,
            "_Blue": 163,
            "_SoundEffect": 8109,
            "_Name": ""
        },
        {
            "_Id": 39,
            "_Rank": 8,
            "_ItemID": 190146651,
            "_ItemRare": 1,
            "_ItemCount": 10,
            "_Ely": 0,
            "_Description": "",
            "_IconFile": 10001312,
            "_IconIndex": 95,
            "_Use": true,
            "_Fx1": 22464,
            "_Fx2": 22474,
            "_Message": "8등이다",
            "_Red": 179,
            "_Green": 163,
            "_Blue": 163,
            "_SoundEffect": 8109,
            "_Name": ""
        },
        {
            "_Id": 40,
            "_Rank": 8,
            "_ItemID": 170194228,
            "_ItemRare": 1,
            "_ItemCount": 1,
            "_Ely": 0,
            "_Description": "",
            "_IconFile": 10001305,
            "_IconIndex": 40,
            "_Use": true,
            "_Fx1": 22464,
            "_Fx2": 22474,
            "_Message": "8등이다",
            "_Red": 179,
            "_Green": 163,
            "_Blue": 163,
            "_SoundEffect": 8109,
            "_Name": ""
        },
        {
            "_Id": 41,
            "_Rank": 8,
            "_ItemID": 190147983,
            "_ItemRare": 1,
            "_ItemCount": 10,
            "_Ely": 0,
            "_Description": "",
            "_IconFile": 10001325,
            "_IconIndex": 70,
            "_Use": true,
            "_Fx1": 22464,
            "_Fx2": 22474,
            "_Message": "8등이다",
            "_Red": 179,
            "_Green": 163,
            "_Blue": 163,
            "_SoundEffect": 8109,
            "_Name": ""
        },
        {
            "_Id": 42,
            "_Rank": 8,
            "_ItemID": 190144674,
            "_ItemRare": 1,
            "_ItemCount": 10,
            "_Ely": 0,
            "_Description": "",
            "_IconFile": 10001309,
            "_IconIndex": 7,
            "_Use": true,
            "_Fx1": 22464,
            "_Fx2": 22474,
            "_Message": "8등이다",
            "_Red": 179,
            "_Green": 163,
            "_Blue": 163,
            "_SoundEffect": 8109,
            "_Name": ""
        },
        {
            "_Id": 43,
            "_Rank": 9,
            "_ItemID": 190146651,
            "_ItemRare": 1,
            "_ItemCount": 5,
            "_Ely": 0,
            "_Description": "",
            "_IconFile": 10001312,
            "_IconIndex": 95,
            "_Use": true,
            "_Fx1": 22465,
            "_Fx2": 22475,
            "_Message": "9등이다",
            "_Red": 179,
            "_Green": 163,
            "_Blue": 163,
            "_SoundEffect": 8109,
            "_Name": ""
        },
        {
            "_Id": 44,
            "_Rank": 9,
            "_ItemID": 190147983,
            "_ItemRare": 1,
            "_ItemCount": 5,
            "_Ely": 0,
            "_Description": "",
            "_IconFile": 10001325,
            "_IconIndex": 70,
            "_Use": true,
            "_Fx1": 22465,
            "_Fx2": 22475,
            "_Message": "9등이다",
            "_Red": 179,
            "_Green": 163,
            "_Blue": 163,
            "_SoundEffect": 8109,
            "_Name": ""
        },
        {
            "_Id": 45,
            "_Rank": 9,
            "_ItemID": 190144674,
            "_ItemRare": 1,
            "_ItemCount": 5,
            "_Ely": 0,
            "_Description": "",
            "_IconFile": 10001309,
            "_IconIndex": 7,
            "_Use": true,
            "_Fx1": 22465,
            "_Fx2": 22475,
            "_Message": "9등이다",
            "_Red": 179,
            "_Green": 163,
            "_Blue": 163,
            "_SoundEffect": 8109,
            "_Name": ""
        },
        {
            "_Id": 46,
            "_Rank": 10,
            "_ItemID": 170171241,
            "_ItemRare": 1,
            "_ItemCount": 2,
            "_Ely": 0,
            "_Description": "",
            "_IconFile": 10001314,
            "_IconIndex": 87,
            "_Use": true,
            "_Fx1": 22466,
            "_Fx2": 22476,
            "_Message": "10등이다",
            "_Red": 179,
            "_Green": 163,
            "_Blue": 163,
            "_SoundEffect": 8109,
            "_Name": ""
        }
    ]
}